dl_lab_exam_07/__init__.py
dl_lab_exam_07/__main__.py
dl_lab_exam_07/cli.py
dl_lab_exam_07/core.py
dl_lab_exam_07-0.3.0.dist-info/METADATA
dl_lab_exam_07-0.3.0.dist-info/WHEEL
dl_lab_exam_07-0.3.0.dist-info/top_level.txt
dl_lab_exam_07-0.3.0.dist-info/RECORD
