Metadata-Version: 2.4
Name: dl-lab-exam-07
Version: 0.3.0
Summary: Deep learning lab project
Home-page: https://example.com/dl_lab
Author: Your Name
Author-email: lilly <reddylilly013@gmail.com>
License: MIT
Requires-Python: >=3.8
